README.md
setup.py
kinton/__init__.py
kinton/db_client.py
kinton/exceptions.py
kinton/fields.py
kinton/queryset.py
kinton/queryset_result.py
kinton/related.py
kinton/utils.py
kinton/models/__init__.py
kinton/models/meta.py
kinton/models/model.py
kinton_orm.egg-info/PKG-INFO
kinton_orm.egg-info/SOURCES.txt
kinton_orm.egg-info/dependency_links.txt
kinton_orm.egg-info/requires.txt
kinton_orm.egg-info/top_level.txt
tests/__init__.py
tests/factories.py
tests/models.py
tests/integration_tests/__init__.py
tests/integration_tests/conftest.py
tests/integration_tests/test_foreign_relationship.py
tests/integration_tests/test_many_to_many_relationship.py
tests/integration_tests/test_model.py
tests/unit_tests/__init__.py
tests/unit_tests/test_model.py