Metadata-Version: 1.2
Name: kinton-orm
Version: 0.0.1
Summary: async python orm
Home-page: https://github.com/pity7736/kinton-orm
Author: Julián Cortés
Author-email: julian.cortes77@pm.me
License: UNKNOWN
Keywords: async orm postgres database
Platform: UNKNOWN
Requires-Python: >=3.7
